vislotan/__init__.py
vislotan/vislotan.py
vislotan-0.0.4.dist-info/licenses/LICENSE
vislotan-0.0.4.dist-info/METADATA
vislotan-0.0.4.dist-info/WHEEL
vislotan-0.0.4.dist-info/top_level.txt
vislotan-0.0.4.dist-info/RECORD
